ScipyLectureNotesZhongwenbanFix1/README.md
ScipyLectureNotesZhongwenbanFix1/__init__.py
ScipyLectureNotesZhongwenbanFix1/__main__.py
ScipyLectureNotesZhongwenbanFix1/file.epub
ScipyLectureNotesZhongwenbanFix1/index.html
ScipyLectureNotesZhongwenbanFix1/css/__init__.py
ScipyLectureNotesZhongwenbanFix1/css/annotations.css
ScipyLectureNotesZhongwenbanFix1/css/main.css
ScipyLectureNotesZhongwenbanFix1/css/normalize.css
ScipyLectureNotesZhongwenbanFix1/css/popup.css
ScipyLectureNotesZhongwenbanFix1/font/__init__.py
ScipyLectureNotesZhongwenbanFix1/font/fontello.eot
ScipyLectureNotesZhongwenbanFix1/font/fontello.svg
ScipyLectureNotesZhongwenbanFix1/font/fontello.ttf
ScipyLectureNotesZhongwenbanFix1/font/fontello.woff
ScipyLectureNotesZhongwenbanFix1/img/__init__.py
ScipyLectureNotesZhongwenbanFix1/img/annotator-glyph-sprite.png
ScipyLectureNotesZhongwenbanFix1/img/annotator-icon-sprite.png
ScipyLectureNotesZhongwenbanFix1/img/apple-touch-icon.png
ScipyLectureNotesZhongwenbanFix1/img/cancelfullscreen.png
ScipyLectureNotesZhongwenbanFix1/img/close.png
ScipyLectureNotesZhongwenbanFix1/img/fullscreen.png
ScipyLectureNotesZhongwenbanFix1/img/loader.gif
ScipyLectureNotesZhongwenbanFix1/img/menu-icon.png
ScipyLectureNotesZhongwenbanFix1/img/save.png
ScipyLectureNotesZhongwenbanFix1/img/saved.png
ScipyLectureNotesZhongwenbanFix1/img/settings-s.png
ScipyLectureNotesZhongwenbanFix1/img/settings.png
ScipyLectureNotesZhongwenbanFix1/img/star.png
ScipyLectureNotesZhongwenbanFix1/js/__init__.py
ScipyLectureNotesZhongwenbanFix1/js/epub.js
ScipyLectureNotesZhongwenbanFix1/js/epub.min.js
ScipyLectureNotesZhongwenbanFix1/js/epub.min.map
ScipyLectureNotesZhongwenbanFix1/js/hooks.min.js
ScipyLectureNotesZhongwenbanFix1/js/hooks.min.map
ScipyLectureNotesZhongwenbanFix1/js/reader.js
ScipyLectureNotesZhongwenbanFix1/js/reader.js.map
ScipyLectureNotesZhongwenbanFix1/js/reader.min.js
ScipyLectureNotesZhongwenbanFix1/js/reader.min.map
ScipyLectureNotesZhongwenbanFix1/js/hooks/__init__.py
scipy_lecture_notes_zhongwenban_fix1-2024.3.2.0.dist-info/METADATA
scipy_lecture_notes_zhongwenban_fix1-2024.3.2.0.dist-info/WHEEL
scipy_lecture_notes_zhongwenban_fix1-2024.3.2.0.dist-info/entry_points.txt
scipy_lecture_notes_zhongwenban_fix1-2024.3.2.0.dist-info/top_level.txt
scipy_lecture_notes_zhongwenban_fix1-2024.3.2.0.dist-info/RECORD
